pymain/__init__.py
pymain/pymain.py
pymain/version.py
pymain-0.3.1.dist-info/DESCRIPTION.rst
pymain-0.3.1.dist-info/METADATA
pymain-0.3.1.dist-info/RECORD
pymain-0.3.1.dist-info/WHEEL
pymain-0.3.1.dist-info/metadata.json
pymain-0.3.1.dist-info/top_level.txt
