Metadata-Version: 2.0
Name: pymain
Version: 0.3.1
Summary: A simplified interface for your main function.
Home-page: https://github.com/jasongraffius/pymain
Author: Jason Graffius
Author-email: UNKNOWN
License: MIT
Keywords: main arguments option argparse
Platform: UNKNOWN
Classifier: Development Status :: 3 - Alpha
Classifier: Environment :: Console
Classifier: Intended Audience :: Developers
Classifier: License :: OSI Approved :: MIT License
Classifier: Operating System :: OS Independent
Classifier: Programming Language :: Python :: 3 :: Only
Classifier: Topic :: Software Development :: User Interfaces
Classifier: Topic :: Utilities
